topsis-aman.py
topsis.py
topsis_aman.py
TOPSIS_Aman_101803543-0.0.2.dist-info/LICENSE.txt
TOPSIS_Aman_101803543-0.0.2.dist-info/METADATA
TOPSIS_Aman_101803543-0.0.2.dist-info/WHEEL
TOPSIS_Aman_101803543-0.0.2.dist-info/top_level.txt
TOPSIS_Aman_101803543-0.0.2.dist-info/RECORD
