Metadata-Version: 2.1
Name: TOPSIS-Aman-101803543
Version: 0.0.2
Summary: TOPSIS Package
Home-page: UNKNOWN
Author: Aman Singla
Author-email: asingla2_be18@thapar.edu
License: UNKNOWN
Platform: UNKNOWN
Classifier: Programming Language :: Python :: 3
Classifier: Programming Language :: Python :: 3.6
Classifier: Programming Language :: Python :: 3.7
Classifier: License :: OSI Approved :: MIT License
Classifier: Operating System :: OS Independent
